krbalancing.cpython-38-darwin.so
krbalancing-0.5.0a3.dist-info/METADATA
krbalancing-0.5.0a3.dist-info/WHEEL
krbalancing-0.5.0a3.dist-info/top_level.txt
krbalancing-0.5.0a3.dist-info/RECORD
