Metadata-Version: 2.1
Name: krbalancing
Version: 0.5.0a3
Summary: A c++ extension for python to balance a matrix using KR method
Home-page: UNKNOWN
Author: Leily Rabbani
Author-email: leila.rabbani@gmail.com
Maintainer: Dilawar Singh
Maintainer-email: dilawar.s.rajput@gmail.com
License: UNKNOWN
Platform: UNKNOWN
